thenewboston/__init__.py
thenewboston/accounts/__init__.py
thenewboston/accounts/key_files.py
thenewboston/accounts/manage.py
thenewboston/argparser/__init__.py
thenewboston/argparser/validators.py
thenewboston/base_classes/__init__.py
thenewboston/base_classes/fetch_primary_validator_config.py
thenewboston/base_classes/initialize_node.py
thenewboston/blocks/__init__.py
thenewboston/blocks/block.py
thenewboston/blocks/signatures.py
thenewboston/constants/__init__.py
thenewboston/constants/clean.py
thenewboston/constants/crawl.py
thenewboston/constants/errors.py
thenewboston/constants/network.py
thenewboston/environment/__init__.py
thenewboston/environment/environment_variables.py
thenewboston/factories/__init__.py
thenewboston/factories/confirmation_service.py
thenewboston/factories/created_modified.py
thenewboston/factories/network_node.py
thenewboston/factories/network_transaction.py
thenewboston/factories/network_validator.py
thenewboston/models/__init__.py
thenewboston/models/confirmation_service.py
thenewboston/models/created_modified.py
thenewboston/models/network_node.py
thenewboston/models/network_transaction.py
thenewboston/models/network_validator.py
thenewboston/serializers/__init__.py
thenewboston/serializers/account_balance.py
thenewboston/serializers/configuration.py
thenewboston/serializers/confirmation_block_message.py
thenewboston/serializers/message.py
thenewboston/serializers/network_block.py
thenewboston/serializers/network_transaction.py
thenewboston/serializers/primary_validator.py
thenewboston/third_party/__init__.py
thenewboston/third_party/django_redis/__init__.py
thenewboston/third_party/django_redis/pool.py
thenewboston/third_party/factory/__init__.py
thenewboston/third_party/factory/utils.py
thenewboston/third_party/pytest/__init__.py
thenewboston/third_party/pytest/asserts.py
thenewboston/third_party/pytest/client.py
thenewboston/transactions/__init__.py
thenewboston/transactions/validation.py
thenewboston/utils/__init__.py
thenewboston_ml_dev-0.2.3.dist-info/LICENSE
thenewboston_ml_dev-0.2.3.dist-info/METADATA
thenewboston_ml_dev-0.2.3.dist-info/WHEEL
thenewboston_ml_dev-0.2.3.dist-info/top_level.txt
thenewboston_ml_dev-0.2.3.dist-info/RECORD
