Metadata-Version: 2.1
Name: thenewboston-ml-dev
Version: 0.2.3
Summary: UNKNOWN
Home-page: https://github.com/thenewboston-developers/thenewboston-python
Author: Bucky Roberts
Author-email: buckyroberts@gmail.com
Maintainer: Thenewboston
License: MIT
Platform: UNKNOWN
Requires-Python: >=3.7
Requires-Dist: Django (==3.1.8)
Requires-Dist: PTable (==0.9.2)
Requires-Dist: PyNaCl (==1.4.0)
Requires-Dist: channels-redis (==2.4.2)
Requires-Dist: channels (==2.4.0)
Requires-Dist: django-cors-headers (==3.7.0)
Requires-Dist: django-debug-toolbar (==3.2)
Requires-Dist: django-filter (==2.4.0)
Requires-Dist: django-redis (==4.12.1)
Requires-Dist: djangorestframework (==3.12.2)
Requires-Dist: factory-boy (==3.2.0)
Requires-Dist: flake8-bugbear (==20.11.1)
Requires-Dist: flake8-builtins (==1.5.3)
Requires-Dist: flake8-coding (==1.3.2)
Requires-Dist: flake8-docstrings (==1.5.0)
Requires-Dist: flake8-import-order (==0.18.1)
Requires-Dist: flake8-polyfill (==1.0.2)
Requires-Dist: flake8-quotes (==3.2.0)
Requires-Dist: flake8 (==3.8.4)
Requires-Dist: freezegun (==1.1.0)
Requires-Dist: iptools (==0.7.0)
Requires-Dist: pycodestyle (==2.6.0)
Requires-Dist: pytest-asyncio (==0.14.0)
Requires-Dist: pytest-cov (==2.11.1)
Requires-Dist: pytest-django (==4.1.0)
Requires-Dist: pytest-xdist (==2.2.1)
Requires-Dist: pytest (==6.2.2)
Requires-Dist: requests-mock (==1.8.0)
Requires-Dist: requests (==2.25.1)
Requires-Dist: sentry-sdk (==0.19.5)
Requires-Dist: setuptools (==50.3.2)
Requires-Dist: wheel (==0.35.1)
